AUTHORS.txt
CHANGES.rst
CLASSIFIERS.txt
LICENSE
MANIFEST.in
README.rst
REQUIREMENTS.txt
setup.py
flask_logmanager/__init__.py
flask_logmanager/__init__.pyc
flask_logmanager/main.py
flask_logmanager/main.pyc
flask_logmanager/util.py
flask_logmanager/util.pyc
flask_logmanager.egg-info/PKG-INFO
flask_logmanager.egg-info/SOURCES.txt
flask_logmanager.egg-info/dependency_links.txt
flask_logmanager.egg-info/requires.txt
flask_logmanager.egg-info/top_level.txt
flask_logmanager/__pycache__/__init__.cpython-37.pyc
flask_logmanager/__pycache__/main.cpython-37.pyc
flask_logmanager/__pycache__/util.cpython-37.pyc
flask_logmanager/controllers/__init__.py
flask_logmanager/controllers/__init__.pyc
flask_logmanager/controllers/logger_controller.py
flask_logmanager/controllers/logger_controller.pyc
flask_logmanager/controllers/__pycache__/__init__.cpython-37.pyc
flask_logmanager/controllers/__pycache__/logger_controller.cpython-37.pyc
flask_logmanager/models/__init__.py
flask_logmanager/models/__init__.pyc
flask_logmanager/models/base_model_.py
flask_logmanager/models/base_model_.pyc
flask_logmanager/models/error_model.py
flask_logmanager/models/error_model.pyc
flask_logmanager/models/logger.py
flask_logmanager/models/logger.pyc
flask_logmanager/models/loggers.py
flask_logmanager/models/loggers.pyc
flask_logmanager/models/__pycache__/__init__.cpython-37.pyc
flask_logmanager/models/__pycache__/base_model_.cpython-37.pyc
flask_logmanager/models/__pycache__/error_model.cpython-37.pyc
flask_logmanager/models/__pycache__/logger.cpython-37.pyc
flask_logmanager/models/__pycache__/loggers.cpython-37.pyc
flask_logmanager/swagger-ui/index.html
flask_logmanager/swagger-ui/o2c.html
flask_logmanager/swagger-ui/swagger-ui.js
flask_logmanager/swagger-ui/swagger-ui.min.js
flask_logmanager/swagger-ui/swagger.yaml
flask_logmanager/swagger-ui/css/print.css
flask_logmanager/swagger-ui/css/reset.css
flask_logmanager/swagger-ui/css/screen.css
flask_logmanager/swagger-ui/css/style.css
flask_logmanager/swagger-ui/css/typography.css
flask_logmanager/swagger-ui/fonts/DroidSans-Bold.ttf
flask_logmanager/swagger-ui/fonts/DroidSans.ttf
flask_logmanager/swagger-ui/images/collapse.gif
